{
  "arrivals": [],
  "departures": [
    {
      "time": "0000",
      "callsign": "F1",
      "appear_time": "0000",
      "model": "A319",
      "gate": "58B",
      "airport": "SJC",
      "runway": "10R/28L",
      "spot": "S3"
    },
    {
      "time": "0001",
      "callsign": "F2",
      "appear_time": "0001",
      "model": "A319",
      "gate": "51A",
      "airport": "SJC",
      "runway": "10R/28L",
      "spot": "S2"
    },
    {
      "time": "0002",
      "callsign": "F3",
      "appear_time": "0002",
      "model": "A319",
      "gate": "55",
      "airport": "SJC",
      "runway": "10R/28L",
      "spot": "S3"
    },
    {
      "time": "0003",
      "callsign": "F4",
      "appear_time": "0003",
      "model": "A319",
      "gate": "51A",
      "airport": "SJC",
      "runway": "10R/28L",
      "spot": "S2"
    },
    {
      "time": "0004",
      "callsign": "F5",
      "appear_time": "0004",
      "model": "A319",
      "gate": "55",
      "airport": "SJC",
      "runway": "10R/28L",
      "spot": "S2"
    },
    {
      "time": "0004",
      "callsign": "F6",
      "appear_time": "0004",
      "model": "A319",
      "gate": "59",
      "airport": "SJC",
      "runway": "10R/28L",
      "spot": "S2"
    },
    {
      "time": "0007",
      "callsign": "F7",
      "appear_time": "0007",
      "model": "A319",
      "gate": "58A",
      "airport": "SJC",
      "runway": "10R/28L",
      "spot": "S2"
    },
    {
      "time": "0009",
      "callsign": "F8",
      "appear_time": "0009",
      "model": "A319",
      "gate": "59",
      "airport": "SJC",
      "runway": "10R/28L",
      "spot": "S3"
    },
    {
      "time": "0011",
      "callsign": "F9",
      "appear_time": "0011",
      "model": "A319",
      "gate": "51A",
      "airport": "SJC",
      "runway": "10R/28L",
      "spot": "S2"
    },
    {
      "time": "0013",
      "callsign": "F10",
      "appear_time": "0013",
      "model": "A319",
      "gate": "53",
      "airport": "SJC",
      "runway": "10R/28L",
      "spot": "S2"
    },
    {
      "time": "0015",
      "callsign": "F11",
      "appear_time": "0015",
      "model": "A319",
      "gate": "56B",
      "airport": "SJC",
      "runway": "10R/28L",
      "spot": "S3"
    },
    {
      "time": "0017",
      "callsign": "F12",
      "appear_time": "0017",
      "model": "A319",
      "gate": "58A",
      "airport": "SJC",
      "runway": "10R/28L",
      "spot": "S2"
    },
    {
      "time": "0019",
      "callsign": "F13",
      "appear_time": "0019",
      "model": "A319",
      "gate": "58B",
      "airport": "SJC",
      "runway": "10R/28L",
      "spot": "S3"
    },
    {
      "time": "0021",
      "callsign": "F14",
      "appear_time": "0021",
      "model": "A319",
      "gate": "52",
      "airport": "SJC",
      "runway": "10R/28L",
      "spot": "S3"
    },
    {
      "time": "0022",
      "callsign": "F15",
      "appear_time": "0022",
      "model": "A319",
      "gate": "58A",
      "airport": "SJC",
      "runway": "10R/28L",
      "spot": "S2"
    },
    {
      "time": "0024",
      "callsign": "F16",
      "appear_time": "0024",
      "model": "A319",
      "gate": "50",
      "airport": "SJC",
      "runway": "10R/28L",
      "spot": "S3"
    },
    {
      "time": "0025",
      "callsign": "F17",
      "appear_time": "0025",
      "model": "A319",
      "gate": "51A",
      "airport": "SJC",
      "runway": "10R/28L",
      "spot": "S2"
    },
    {
      "time": "0027",
      "callsign": "F18",
      "appear_time": "0027",
      "model": "A319",
      "gate": "53",
      "airport": "SJC",
      "runway": "10R/28L",
      "spot": "S2"
    },
    {
      "time": "0029",
      "callsign": "F19",
      "appear_time": "0029",
      "model": "A319",
      "gate": "58B",
      "airport": "SJC",
      "runway": "10R/28L",
      "spot": "S2"
    },
    {
      "time": "0030",
      "callsign": "F20",
      "appear_time": "0030",
      "model": "A319",
      "gate": "59",
      "airport": "SJC",
      "runway": "10R/28L",
      "spot": "S2"
    },
    {
      "time": "0032",
      "callsign": "F21",
      "appear_time": "0032",
      "model": "A319",
      "gate": "53",
      "airport": "SJC",
      "runway": "10R/28L",
      "spot": "S2"
    },
    {
      "time": "0033",
      "callsign": "F22",
      "appear_time": "0033",
      "model": "A319",
      "gate": "54B",
      "airport": "SJC",
      "runway": "10R/28L",
      "spot": "S2"
    },
    {
      "time": "0035",
      "callsign": "F23",
      "appear_time": "0035",
      "model": "A319",
      "gate": "56A",
      "airport": "SJC",
      "runway": "10R/28L",
      "spot": "S3"
    },
    {
      "time": "0037",
      "callsign": "F24",
      "appear_time": "0037",
      "model": "A319",
      "gate": "55",
      "airport": "SJC",
      "runway": "10R/28L",
      "spot": "S3"
    },
    {
      "time": "0038",
      "callsign": "F25",
      "appear_time": "0038",
      "model": "A319",
      "gate": "54B",
      "airport": "SJC",
      "runway": "10R/28L",
      "spot": "S2"
    },
    {
      "time": "0039",
      "callsign": "F26",
      "appear_time": "0039",
      "model": "A319",
      "gate": "50",
      "airport": "SJC",
      "runway": "10R/28L",
      "spot": "S2"
    },
    {
      "time": "0042",
      "callsign": "F27",
      "appear_time": "0042",
      "model": "A319",
      "gate": "54A",
      "airport": "SJC",
      "runway": "10R/28L",
      "spot": "S3"
    },
    {
      "time": "0043",
      "callsign": "F28",
      "appear_time": "0043",
      "model": "A319",
      "gate": "57",
      "airport": "SJC",
      "runway": "10R/28L",
      "spot": "S3"
    },
    {
      "time": "0045",
      "callsign": "F29",
      "appear_time": "0045",
      "model": "A319",
      "gate": "58A",
      "airport": "SJC",
      "runway": "10R/28L",
      "spot": "S3"
    },
    {
      "time": "0048",
      "callsign": "F30",
      "appear_time": "0048",
      "model": "A319",
      "gate": "57",
      "airport": "SJC",
      "runway": "10R/28L",
      "spot": "S2"
    },
    {
      "time": "0049",
      "callsign": "F31",
      "appear_time": "0049",
      "model": "A319",
      "gate": "51A",
      "airport": "SJC",
      "runway": "10R/28L",
      "spot": "S3"
    },
    {
      "time": "0051",
      "callsign": "F32",
      "appear_time": "0051",
      "model": "A319",
      "gate": "54A",
      "airport": "SJC",
      "runway": "10R/28L",
      "spot": "S3"
    },
    {
      "time": "0051",
      "callsign": "F33",
      "appear_time": "0051",
      "model": "A319",
      "gate": "57",
      "airport": "SJC",
      "runway": "10R/28L",
      "spot": "S2"
    },
    {
      "time": "0052",
      "callsign": "F34",
      "appear_time": "0052",
      "model": "A319",
      "gate": "57",
      "airport": "SJC",
      "runway": "10R/28L",
      "spot": "S2"
    },
    {
      "time": "0054",
      "callsign": "F35",
      "appear_time": "0054",
      "model": "A319",
      "gate": "50",
      "airport": "SJC",
      "runway": "10R/28L",
      "spot": "S3"
    },
    {
      "time": "0056",
      "callsign": "F36",
      "appear_time": "0056",
      "model": "A319",
      "gate": "57",
      "airport": "SJC",
      "runway": "10R/28L",
      "spot": "S2"
    },
    {
      "time": "0058",
      "callsign": "F37",
      "appear_time": "0058",
      "model": "A319",
      "gate": "52",
      "airport": "SJC",
      "runway": "10R/28L",
      "spot": "S3"
    },
    {
      "time": "0100",
      "callsign": "F38",
      "appear_time": "0100",
      "model": "A319",
      "gate": "58A",
      "airport": "SJC",
      "runway": "10R/28L",
      "spot": "S2"
    },
    {
      "time": "0101",
      "callsign": "F39",
      "appear_time": "0101",
      "model": "A319",
      "gate": "59",
      "airport": "SJC",
      "runway": "10R/28L",
      "spot": "S2"
    },
    {
      "time": "0102",
      "callsign": "F40",
      "appear_time": "0102",
      "model": "A319",
      "gate": "53",
      "airport": "SJC",
      "runway": "10R/28L",
      "spot": "S2"
    },
    {
      "time": "0104",
      "callsign": "F41",
      "appear_time": "0104",
      "model": "A319",
      "gate": "54A",
      "airport": "SJC",
      "runway": "10R/28L",
      "spot": "S2"
    },
    {
      "time": "0105",
      "callsign": "F42",
      "appear_time": "0105",
      "model": "A319",
      "gate": "51B",
      "airport": "SJC",
      "runway": "10R/28L",
      "spot": "S2"
    },
    {
      "time": "0106",
      "callsign": "F43",
      "appear_time": "0106",
      "model": "A319",
      "gate": "55",
      "airport": "SJC",
      "runway": "10R/28L",
      "spot": "S3"
    },
    {
      "time": "0108",
      "callsign": "F44",
      "appear_time": "0108",
      "model": "A319",
      "gate": "53",
      "airport": "SJC",
      "runway": "10R/28L",
      "spot": "S2"
    },
    {
      "time": "0110",
      "callsign": "F45",
      "appear_time": "0110",
      "model": "A319",
      "gate": "51A",
      "airport": "SJC",
      "runway": "10R/28L",
      "spot": "S3"
    },
    {
      "time": "0111",
      "callsign": "F46",
      "appear_time": "0111",
      "model": "A319",
      "gate": "52",
      "airport": "SJC",
      "runway": "10R/28L",
      "spot": "S3"
    },
    {
      "time": "0112",
      "callsign": "F47",
      "appear_time": "0112",
      "model": "A319",
      "gate": "57",
      "airport": "SJC",
      "runway": "10R/28L",
      "spot": "S3"
    },
    {
      "time": "0114",
      "callsign": "F48",
      "appear_time": "0114",
      "model": "A319",
      "gate": "59",
      "airport": "SJC",
      "runway": "10R/28L",
      "spot": "S2"
    },
    {
      "time": "0116",
      "callsign": "F49",
      "appear_time": "0116",
      "model": "A319",
      "gate": "58B",
      "airport": "SJC",
      "runway": "10R/28L",
      "spot": "S3"
    },
    {
      "time": "0117",
      "callsign": "F50",
      "appear_time": "0117",
      "model": "A319",
      "gate": "53",
      "airport": "SJC",
      "runway": "10R/28L",
      "spot": "S2"
    },
    {
      "time": "0119",
      "callsign": "F51",
      "appear_time": "0119",
      "model": "A319",
      "gate": "54B",
      "airport": "SJC",
      "runway": "10R/28L",
      "spot": "S3"
    },
    {
      "time": "0121",
      "callsign": "F52",
      "appear_time": "0121",
      "model": "A319",
      "gate": "54A",
      "airport": "SJC",
      "runway": "10R/28L",
      "spot": "S2"
    },
    {
      "time": "0123",
      "callsign": "F53",
      "appear_time": "0123",
      "model": "A319",
      "gate": "54A",
      "airport": "SJC",
      "runway": "10R/28L",
      "spot": "S2"
    },
    {
      "time": "0124",
      "callsign": "F54",
      "appear_time": "0124",
      "model": "A319",
      "gate": "52",
      "airport": "SJC",
      "runway": "10R/28L",
      "spot": "S2"
    },
    {
      "time": "0126",
      "callsign": "F55",
      "appear_time": "0126",
      "model": "A319",
      "gate": "54B",
      "airport": "SJC",
      "runway": "10R/28L",
      "spot": "S2"
    },
    {
      "time": "0127",
      "callsign": "F56",
      "appear_time": "0127",
      "model": "A319",
      "gate": "56A",
      "airport": "SJC",
      "runway": "10R/28L",
      "spot": "S2"
    },
    {
      "time": "0129",
      "callsign": "F57",
      "appear_time": "0129",
      "model": "A319",
      "gate": "54A",
      "airport": "SJC",
      "runway": "10R/28L",
      "spot": "S2"
    },
    {
      "time": "0131",
      "callsign": "F58",
      "appear_time": "0131",
      "model": "A319",
      "gate": "57",
      "airport": "SJC",
      "runway": "10R/28L",
      "spot": "S3"
    },
    {
      "time": "0132",
      "callsign": "F59",
      "appear_time": "0132",
      "model": "A319",
      "gate": "53",
      "airport": "SJC",
      "runway": "10R/28L",
      "spot": "S2"
    },
    {
      "time": "0134",
      "callsign": "F60",
      "appear_time": "0134",
      "model": "A319",
      "gate": "54A",
      "airport": "SJC",
      "runway": "10R/28L",
      "spot": "S2"
    },
    {
      "time": "0135",
      "callsign": "F61",
      "appear_time": "0135",
      "model": "A319",
      "gate": "52",
      "airport": "SJC",
      "runway": "10R/28L",
      "spot": "S3"
    },
    {
      "time": "0136",
      "callsign": "F62",
      "appear_time": "0136",
      "model": "A319",
      "gate": "58A",
      "airport": "SJC",
      "runway": "10R/28L",
      "spot": "S3"
    },
    {
      "time": "0138",
      "callsign": "F63",
      "appear_time": "0138",
      "model": "A319",
      "gate": "50",
      "airport": "SJC",
      "runway": "10R/28L",
      "spot": "S3"
    },
    {
      "time": "0140",
      "callsign": "F64",
      "appear_time": "0140",
      "model": "A319",
      "gate": "58B",
      "airport": "SJC",
      "runway": "10R/28L",
      "spot": "S2"
    },
    {
      "time": "0141",
      "callsign": "F65",
      "appear_time": "0141",
      "model": "A319",
      "gate": "51B",
      "airport": "SJC",
      "runway": "10R/28L",
      "spot": "S3"
    },
    {
      "time": "0142",
      "callsign": "F66",
      "appear_time": "0142",
      "model": "A319",
      "gate": "51A",
      "airport": "SJC",
      "runway": "10R/28L",
      "spot": "S2"
    },
    {
      "time": "0143",
      "callsign": "F67",
      "appear_time": "0143",
      "model": "A319",
      "gate": "54A",
      "airport": "SJC",
      "runway": "10R/28L",
      "spot": "S3"
    },
    {
      "time": "0144",
      "callsign": "F68",
      "appear_time": "0144",
      "model": "A319",
      "gate": "51A",
      "airport": "SJC",
      "runway": "10R/28L",
      "spot": "S3"
    },
    {
      "time": "0146",
      "callsign": "F69",
      "appear_time": "0146",
      "model": "A319",
      "gate": "51A",
      "airport": "SJC",
      "runway": "10R/28L",
      "spot": "S2"
    },
    {
      "time": "0146",
      "callsign": "F70",
      "appear_time": "0146",
      "model": "A319",
      "gate": "54B",
      "airport": "SJC",
      "runway": "10R/28L",
      "spot": "S3"
    },
    {
      "time": "0148",
      "callsign": "F71",
      "appear_time": "0148",
      "model": "A319",
      "gate": "58B",
      "airport": "SJC",
      "runway": "10R/28L",
      "spot": "S2"
    },
    {
      "time": "0150",
      "callsign": "F72",
      "appear_time": "0150",
      "model": "A319",
      "gate": "51A",
      "airport": "SJC",
      "runway": "10R/28L",
      "spot": "S2"
    },
    {
      "time": "0152",
      "callsign": "F73",
      "appear_time": "0152",
      "model": "A319",
      "gate": "50",
      "airport": "SJC",
      "runway": "10R/28L",
      "spot": "S2"
    },
    {
      "time": "0152",
      "callsign": "F74",
      "appear_time": "0152",
      "model": "A319",
      "gate": "59",
      "airport": "SJC",
      "runway": "10R/28L",
      "spot": "S3"
    },
    {
      "time": "0154",
      "callsign": "F75",
      "appear_time": "0154",
      "model": "A319",
      "gate": "50",
      "airport": "SJC",
      "runway": "10R/28L",
      "spot": "S2"
    },
    {
      "time": "0156",
      "callsign": "F76",
      "appear_time": "0156",
      "model": "A319",
      "gate": "57",
      "airport": "SJC",
      "runway": "10R/28L",
      "spot": "S3"
    },
    {
      "time": "0158",
      "callsign": "F77",
      "appear_time": "0158",
      "model": "A319",
      "gate": "58A",
      "airport": "SJC",
      "runway": "10R/28L",
      "spot": "S3"
    },
    {
      "time": "0159",
      "callsign": "F78",
      "appear_time": "0159",
      "model": "A319",
      "gate": "51B",
      "airport": "SJC",
      "runway": "10R/28L",
      "spot": "S3"
    },
    {
      "time": "0200",
      "callsign": "F79",
      "appear_time": "0200",
      "model": "A319",
      "gate": "54B",
      "airport": "SJC",
      "runway": "10R/28L",
      "spot": "S3"
    },
    {
      "time": "0201",
      "callsign": "F80",
      "appear_time": "0201",
      "model": "A319",
      "gate": "51B",
      "airport": "SJC",
      "runway": "10R/28L",
      "spot": "S3"
    },
    {
      "time": "0202",
      "callsign": "F81",
      "appear_time": "0202",
      "model": "A319",
      "gate": "54B",
      "airport": "SJC",
      "runway": "10R/28L",
      "spot": "S2"
    },
    {
      "time": "0203",
      "callsign": "F82",
      "appear_time": "0203",
      "model": "A319",
      "gate": "54A",
      "airport": "SJC",
      "runway": "10R/28L",
      "spot": "S2"
    },
    {
      "time": "0205",
      "callsign": "F83",
      "appear_time": "0205",
      "model": "A319",
      "gate": "50",
      "airport": "SJC",
      "runway": "10R/28L",
      "spot": "S3"
    },
    {
      "time": "0205",
      "callsign": "F84",
      "appear_time": "0205",
      "model": "A319",
      "gate": "58B",
      "airport": "SJC",
      "runway": "10R/28L",
      "spot": "S3"
    },
    {
      "time": "0207",
      "callsign": "F85",
      "appear_time": "0207",
      "model": "A319",
      "gate": "55",
      "airport": "SJC",
      "runway": "10R/28L",
      "spot": "S3"
    },
    {
      "time": "0208",
      "callsign": "F86",
      "appear_time": "0208",
      "model": "A319",
      "gate": "53",
      "airport": "SJC",
      "runway": "10R/28L",
      "spot": "S2"
    },
    {
      "time": "0209",
      "callsign": "F87",
      "appear_time": "0209",
      "model": "A319",
      "gate": "55",
      "airport": "SJC",
      "runway": "10R/28L",
      "spot": "S2"
    },
    {
      "time": "0210",
      "callsign": "F88",
      "appear_time": "0210",
      "model": "A319",
      "gate": "56A",
      "airport": "SJC",
      "runway": "10R/28L",
      "spot": "S3"
    },
    {
      "time": "0211",
      "callsign": "F89",
      "appear_time": "0211",
      "model": "A319",
      "gate": "55",
      "airport": "SJC",
      "runway": "10R/28L",
      "spot": "S2"
    },
    {
      "time": "0212",
      "callsign": "F90",
      "appear_time": "0212",
      "model": "A319",
      "gate": "53",
      "airport": "SJC",
      "runway": "10R/28L",
      "spot": "S2"
    },
    {
      "time": "0214",
      "callsign": "F91",
      "appear_time": "0214",
      "model": "A319",
      "gate": "57",
      "airport": "SJC",
      "runway": "10R/28L",
      "spot": "S2"
    },
    {
      "time": "0215",
      "callsign": "F92",
      "appear_time": "0215",
      "model": "A319",
      "gate": "55",
      "airport": "SJC",
      "runway": "10R/28L",
      "spot": "S3"
    },
    {
      "time": "0216",
      "callsign": "F93",
      "appear_time": "0216",
      "model": "A319",
      "gate": "54A",
      "airport": "SJC",
      "runway": "10R/28L",
      "spot": "S2"
    },
    {
      "time": "0218",
      "callsign": "F94",
      "appear_time": "0218",
      "model": "A319",
      "gate": "50",
      "airport": "SJC",
      "runway": "10R/28L",
      "spot": "S2"
    },
    {
      "time": "0220",
      "callsign": "F95",
      "appear_time": "0220",
      "model": "A319",
      "gate": "56B",
      "airport": "SJC",
      "runway": "10R/28L",
      "spot": "S3"
    },
    {
      "time": "0221",
      "callsign": "F96",
      "appear_time": "0221",
      "model": "A319",
      "gate": "54A",
      "airport": "SJC",
      "runway": "10R/28L",
      "spot": "S2"
    },
    {
      "time": "0223",
      "callsign": "F97",
      "appear_time": "0223",
      "model": "A319",
      "gate": "54A",
      "airport": "SJC",
      "runway": "10R/28L",
      "spot": "S3"
    },
    {
      "time": "0225",
      "callsign": "F98",
      "appear_time": "0225",
      "model": "A319",
      "gate": "50",
      "airport": "SJC",
      "runway": "10R/28L",
      "spot": "S2"
    },
    {
      "time": "0226",
      "callsign": "F99",
      "appear_time": "0226",
      "model": "A319",
      "gate": "56A",
      "airport": "SJC",
      "runway": "10R/28L",
      "spot": "S2"
    },
    {
      "time": "0227",
      "callsign": "F100",
      "appear_time": "0227",
      "model": "A319",
      "gate": "54B",
      "airport": "SJC",
      "runway": "10R/28L",
      "spot": "S3"
    },
    {
      "time": "0230",
      "callsign": "F101",
      "appear_time": "0230",
      "model": "A319",
      "gate": "52",
      "airport": "SJC",
      "runway": "10R/28L",
      "spot": "S3"
    },
    {
      "time": "0231",
      "callsign": "F102",
      "appear_time": "0231",
      "model": "A319",
      "gate": "51B",
      "airport": "SJC",
      "runway": "10R/28L",
      "spot": "S3"
    },
    {
      "time": "0232",
      "callsign": "F103",
      "appear_time": "0232",
      "model": "A319",
      "gate": "55",
      "airport": "SJC",
      "runway": "10R/28L",
      "spot": "S3"
    },
    {
      "time": "0233",
      "callsign": "F104",
      "appear_time": "0233",
      "model": "A319",
      "gate": "55",
      "airport": "SJC",
      "runway": "10R/28L",
      "spot": "S3"
    },
    {
      "time": "0234",
      "callsign": "F105",
      "appear_time": "0234",
      "model": "A319",
      "gate": "58A",
      "airport": "SJC",
      "runway": "10R/28L",
      "spot": "S2"
    },
    {
      "time": "0236",
      "callsign": "F106",
      "appear_time": "0236",
      "model": "A319",
      "gate": "54A",
      "airport": "SJC",
      "runway": "10R/28L",
      "spot": "S3"
    },
    {
      "time": "0237",
      "callsign": "F107",
      "appear_time": "0237",
      "model": "A319",
      "gate": "51B",
      "airport": "SJC",
      "runway": "10R/28L",
      "spot": "S2"
    },
    {
      "time": "0238",
      "callsign": "F108",
      "appear_time": "0238",
      "model": "A319",
      "gate": "50",
      "airport": "SJC",
      "runway": "10R/28L",
      "spot": "S2"
    },
    {
      "time": "0240",
      "callsign": "F109",
      "appear_time": "0240",
      "model": "A319",
      "gate": "56B",
      "airport": "SJC",
      "runway": "10R/28L",
      "spot": "S3"
    },
    {
      "time": "0241",
      "callsign": "F110",
      "appear_time": "0241",
      "model": "A319",
      "gate": "55",
      "airport": "SJC",
      "runway": "10R/28L",
      "spot": "S3"
    },
    {
      "time": "0243",
      "callsign": "F111",
      "appear_time": "0243",
      "model": "A319",
      "gate": "58B",
      "airport": "SJC",
      "runway": "10R/28L",
      "spot": "S3"
    },
    {
      "time": "0245",
      "callsign": "F112",
      "appear_time": "0245",
      "model": "A319",
      "gate": "54A",
      "airport": "SJC",
      "runway": "10R/28L",
      "spot": "S2"
    },
    {
      "time": "0246",
      "callsign": "F113",
      "appear_time": "0246",
      "model": "A319",
      "gate": "54A",
      "airport": "SJC",
      "runway": "10R/28L",
      "spot": "S2"
    },
    {
      "time": "0247",
      "callsign": "F114",
      "appear_time": "0247",
      "model": "A319",
      "gate": "54A",
      "airport": "SJC",
      "runway": "10R/28L",
      "spot": "S2"
    },
    {
      "time": "0249",
      "callsign": "F115",
      "appear_time": "0249",
      "model": "A319",
      "gate": "58B",
      "airport": "SJC",
      "runway": "10R/28L",
      "spot": "S3"
    },
    {
      "time": "0251",
      "callsign": "F116",
      "appear_time": "0251",
      "model": "A319",
      "gate": "52",
      "airport": "SJC",
      "runway": "10R/28L",
      "spot": "S3"
    },
    {
      "time": "0252",
      "callsign": "F117",
      "appear_time": "0252",
      "model": "A319",
      "gate": "52",
      "airport": "SJC",
      "runway": "10R/28L",
      "spot": "S2"
    },
    {
      "time": "0254",
      "callsign": "F118",
      "appear_time": "0254",
      "model": "A319",
      "gate": "59",
      "airport": "SJC",
      "runway": "10R/28L",
      "spot": "S3"
    },
    {
      "time": "0256",
      "callsign": "F119",
      "appear_time": "0256",
      "model": "A319",
      "gate": "55",
      "airport": "SJC",
      "runway": "10R/28L",
      "spot": "S3"
    },
    {
      "time": "0257",
      "callsign": "F120",
      "appear_time": "0257",
      "model": "A319",
      "gate": "57",
      "airport": "SJC",
      "runway": "10R/28L",
      "spot": "S3"
    },
    {
      "time": "0300",
      "callsign": "F121",
      "appear_time": "0300",
      "model": "A319",
      "gate": "51B",
      "airport": "SJC",
      "runway": "10R/28L",
      "spot": "S3"
    },
    {
      "time": "0301",
      "callsign": "F122",
      "appear_time": "0301",
      "model": "A319",
      "gate": "58A",
      "airport": "SJC",
      "runway": "10R/28L",
      "spot": "S3"
    },
    {
      "time": "0303",
      "callsign": "F123",
      "appear_time": "0303",
      "model": "A319",
      "gate": "54A",
      "airport": "SJC",
      "runway": "10R/28L",
      "spot": "S2"
    },
    {
      "time": "0304",
      "callsign": "F124",
      "appear_time": "0304",
      "model": "A319",
      "gate": "59",
      "airport": "SJC",
      "runway": "10R/28L",
      "spot": "S3"
    },
    {
      "time": "0306",
      "callsign": "F125",
      "appear_time": "0306",
      "model": "A319",
      "gate": "51B",
      "airport": "SJC",
      "runway": "10R/28L",
      "spot": "S3"
    },
    {
      "time": "0308",
      "callsign": "F126",
      "appear_time": "0308",
      "model": "A319",
      "gate": "53",
      "airport": "SJC",
      "runway": "10R/28L",
      "spot": "S3"
    },
    {
      "time": "0309",
      "callsign": "F127",
      "appear_time": "0309",
      "model": "A319",
      "gate": "56A",
      "airport": "SJC",
      "runway": "10R/28L",
      "spot": "S2"
    },
    {
      "time": "0311",
      "callsign": "F128",
      "appear_time": "0311",
      "model": "A319",
      "gate": "54B",
      "airport": "SJC",
      "runway": "10R/28L",
      "spot": "S2"
    },
    {
      "time": "0313",
      "callsign": "F129",
      "appear_time": "0313",
      "model": "A319",
      "gate": "56B",
      "airport": "SJC",
      "runway": "10R/28L",
      "spot": "S2"
    },
    {
      "time": "0314",
      "callsign": "F130",
      "appear_time": "0314",
      "model": "A319",
      "gate": "58B",
      "airport": "SJC",
      "runway": "10R/28L",
      "spot": "S3"
    },
    {
      "time": "0316",
      "callsign": "F131",
      "appear_time": "0316",
      "model": "A319",
      "gate": "56A",
      "airport": "SJC",
      "runway": "10R/28L",
      "spot": "S2"
    },
    {
      "time": "0317",
      "callsign": "F132",
      "appear_time": "0317",
      "model": "A319",
      "gate": "55",
      "airport": "SJC",
      "runway": "10R/28L",
      "spot": "S2"
    },
    {
      "time": "0319",
      "callsign": "F133",
      "appear_time": "0319",
      "model": "A319",
      "gate": "58A",
      "airport": "SJC",
      "runway": "10R/28L",
      "spot": "S2"
    },
    {
      "time": "0321",
      "callsign": "F134",
      "appear_time": "0321",
      "model": "A319",
      "gate": "51B",
      "airport": "SJC",
      "runway": "10R/28L",
      "spot": "S3"
    },
    {
      "time": "0323",
      "callsign": "F135",
      "appear_time": "0323",
      "model": "A319",
      "gate": "58B",
      "airport": "SJC",
      "runway": "10R/28L",
      "spot": "S3"
    },
    {
      "time": "0323",
      "callsign": "F136",
      "appear_time": "0323",
      "model": "A319",
      "gate": "51A",
      "airport": "SJC",
      "runway": "10R/28L",
      "spot": "S2"
    },
    {
      "time": "0324",
      "callsign": "F137",
      "appear_time": "0324",
      "model": "A319",
      "gate": "56B",
      "airport": "SJC",
      "runway": "10R/28L",
      "spot": "S3"
    },
    {
      "time": "0326",
      "callsign": "F138",
      "appear_time": "0326",
      "model": "A319",
      "gate": "51B",
      "airport": "SJC",
      "runway": "10R/28L",
      "spot": "S2"
    },
    {
      "time": "0327",
      "callsign": "F139",
      "appear_time": "0327",
      "model": "A319",
      "gate": "55",
      "airport": "SJC",
      "runway": "10R/28L",
      "spot": "S3"
    },
    {
      "time": "0329",
      "callsign": "F140",
      "appear_time": "0329",
      "model": "A319",
      "gate": "56A",
      "airport": "SJC",
      "runway": "10R/28L",
      "spot": "S3"
    },
    {
      "time": "0330",
      "callsign": "F141",
      "appear_time": "0330",
      "model": "A319",
      "gate": "56A",
      "airport": "SJC",
      "runway": "10R/28L",
      "spot": "S2"
    },
    {
      "time": "0331",
      "callsign": "F142",
      "appear_time": "0331",
      "model": "A319",
      "gate": "51B",
      "airport": "SJC",
      "runway": "10R/28L",
      "spot": "S2"
    },
    {
      "time": "0332",
      "callsign": "F143",
      "appear_time": "0332",
      "model": "A319",
      "gate": "53",
      "airport": "SJC",
      "runway": "10R/28L",
      "spot": "S2"
    },
    {
      "time": "0333",
      "callsign": "F144",
      "appear_time": "0333",
      "model": "A319",
      "gate": "50",
      "airport": "SJC",
      "runway": "10R/28L",
      "spot": "S2"
    },
    {
      "time": "0335",
      "callsign": "F145",
      "appear_time": "0335",
      "model": "A319",
      "gate": "56B",
      "airport": "SJC",
      "runway": "10R/28L",
      "spot": "S2"
    },
    {
      "time": "0338",
      "callsign": "F146",
      "appear_time": "0338",
      "model": "A319",
      "gate": "53",
      "airport": "SJC",
      "runway": "10R/28L",
      "spot": "S2"
    },
    {
      "time": "0340",
      "callsign": "F147",
      "appear_time": "0340",
      "model": "A319",
      "gate": "58A",
      "airport": "SJC",
      "runway": "10R/28L",
      "spot": "S3"
    },
    {
      "time": "0342",
      "callsign": "F148",
      "appear_time": "0342",
      "model": "A319",
      "gate": "54A",
      "airport": "SJC",
      "runway": "10R/28L",
      "spot": "S2"
    },
    {
      "time": "0343",
      "callsign": "F149",
      "appear_time": "0343",
      "model": "A319",
      "gate": "52",
      "airport": "SJC",
      "runway": "10R/28L",
      "spot": "S2"
    },
    {
      "time": "0344",
      "callsign": "F150",
      "appear_time": "0344",
      "model": "A319",
      "gate": "53",
      "airport": "SJC",
      "runway": "10R/28L",
      "spot": "S2"
    },
    {
      "time": "0345",
      "callsign": "F151",
      "appear_time": "0345",
      "model": "A319",
      "gate": "54A",
      "airport": "SJC",
      "runway": "10R/28L",
      "spot": "S3"
    },
    {
      "time": "0347",
      "callsign": "F152",
      "appear_time": "0347",
      "model": "A319",
      "gate": "54B",
      "airport": "SJC",
      "runway": "10R/28L",
      "spot": "S2"
    },
    {
      "time": "0348",
      "callsign": "F153",
      "appear_time": "0348",
      "model": "A319",
      "gate": "56A",
      "airport": "SJC",
      "runway": "10R/28L",
      "spot": "S2"
    },
    {
      "time": "0349",
      "callsign": "F154",
      "appear_time": "0349",
      "model": "A319",
      "gate": "52",
      "airport": "SJC",
      "runway": "10R/28L",
      "spot": "S2"
    },
    {
      "time": "0350",
      "callsign": "F155",
      "appear_time": "0350",
      "model": "A319",
      "gate": "51A",
      "airport": "SJC",
      "runway": "10R/28L",
      "spot": "S2"
    },
    {
      "time": "0351",
      "callsign": "F156",
      "appear_time": "0351",
      "model": "A319",
      "gate": "52",
      "airport": "SJC",
      "runway": "10R/28L",
      "spot": "S2"
    },
    {
      "time": "0352",
      "callsign": "F157",
      "appear_time": "0352",
      "model": "A319",
      "gate": "59",
      "airport": "SJC",
      "runway": "10R/28L",
      "spot": "S2"
    },
    {
      "time": "0353",
      "callsign": "F158",
      "appear_time": "0353",
      "model": "A319",
      "gate": "54B",
      "airport": "SJC",
      "runway": "10R/28L",
      "spot": "S2"
    },
    {
      "time": "0356",
      "callsign": "F159",
      "appear_time": "0356",
      "model": "A319",
      "gate": "54B",
      "airport": "SJC",
      "runway": "10R/28L",
      "spot": "S3"
    },
    {
      "time": "0358",
      "callsign": "F160",
      "appear_time": "0358",
      "model": "A319",
      "gate": "54A",
      "airport": "SJC",
      "runway": "10R/28L",
      "spot": "S3"
    },
    {
      "time": "0359",
      "callsign": "F161",
      "appear_time": "0359",
      "model": "A319",
      "gate": "53",
      "airport": "SJC",
      "runway": "10R/28L",
      "spot": "S3"
    },
    {
      "time": "0359",
      "callsign": "F162",
      "appear_time": "0359",
      "model": "A319",
      "gate": "55",
      "airport": "SJC",
      "runway": "10R/28L",
      "spot": "S2"
    },
    {
      "time": "0400",
      "callsign": "F163",
      "appear_time": "0400",
      "model": "A319",
      "gate": "54A",
      "airport": "SJC",
      "runway": "10R/28L",
      "spot": "S2"
    },
    {
      "time": "0402",
      "callsign": "F164",
      "appear_time": "0402",
      "model": "A319",
      "gate": "55",
      "airport": "SJC",
      "runway": "10R/28L",
      "spot": "S3"
    },
    {
      "time": "0403",
      "callsign": "F165",
      "appear_time": "0403",
      "model": "A319",
      "gate": "54A",
      "airport": "SJC",
      "runway": "10R/28L",
      "spot": "S2"
    },
    {
      "time": "0404",
      "callsign": "F166",
      "appear_time": "0404",
      "model": "A319",
      "gate": "56B",
      "airport": "SJC",
      "runway": "10R/28L",
      "spot": "S3"
    },
    {
      "time": "0406",
      "callsign": "F167",
      "appear_time": "0406",
      "model": "A319",
      "gate": "54A",
      "airport": "SJC",
      "runway": "10R/28L",
      "spot": "S2"
    },
    {
      "time": "0408",
      "callsign": "F168",
      "appear_time": "0408",
      "model": "A319",
      "gate": "58A",
      "airport": "SJC",
      "runway": "10R/28L",
      "spot": "S3"
    },
    {
      "time": "0410",
      "callsign": "F169",
      "appear_time": "0410",
      "model": "A319",
      "gate": "54B",
      "airport": "SJC",
      "runway": "10R/28L",
      "spot": "S2"
    },
    {
      "time": "0412",
      "callsign": "F170",
      "appear_time": "0412",
      "model": "A319",
      "gate": "50",
      "airport": "SJC",
      "runway": "10R/28L",
      "spot": "S2"
    },
    {
      "time": "0414",
      "callsign": "F171",
      "appear_time": "0414",
      "model": "A319",
      "gate": "51B",
      "airport": "SJC",
      "runway": "10R/28L",
      "spot": "S3"
    },
    {
      "time": "0415",
      "callsign": "F172",
      "appear_time": "0415",
      "model": "A319",
      "gate": "56A",
      "airport": "SJC",
      "runway": "10R/28L",
      "spot": "S3"
    },
    {
      "time": "0417",
      "callsign": "F173",
      "appear_time": "0417",
      "model": "A319",
      "gate": "57",
      "airport": "SJC",
      "runway": "10R/28L",
      "spot": "S2"
    },
    {
      "time": "0418",
      "callsign": "F174",
      "appear_time": "0418",
      "model": "A319",
      "gate": "56A",
      "airport": "SJC",
      "runway": "10R/28L",
      "spot": "S3"
    },
    {
      "time": "0420",
      "callsign": "F175",
      "appear_time": "0420",
      "model": "A319",
      "gate": "54B",
      "airport": "SJC",
      "runway": "10R/28L",
      "spot": "S3"
    },
    {
      "time": "0421",
      "callsign": "F176",
      "appear_time": "0421",
      "model": "A319",
      "gate": "56A",
      "airport": "SJC",
      "runway": "10R/28L",
      "spot": "S2"
    },
    {
      "time": "0423",
      "callsign": "F177",
      "appear_time": "0423",
      "model": "A319",
      "gate": "53",
      "airport": "SJC",
      "runway": "10R/28L",
      "spot": "S3"
    },
    {
      "time": "0424",
      "callsign": "F178",
      "appear_time": "0424",
      "model": "A319",
      "gate": "56A",
      "airport": "SJC",
      "runway": "10R/28L",
      "spot": "S2"
    },
    {
      "time": "0425",
      "callsign": "F179",
      "appear_time": "0425",
      "model": "A319",
      "gate": "51A",
      "airport": "SJC",
      "runway": "10R/28L",
      "spot": "S3"
    },
    {
      "time": "0427",
      "callsign": "F180",
      "appear_time": "0427",
      "model": "A319",
      "gate": "52",
      "airport": "SJC",
      "runway": "10R/28L",
      "spot": "S3"
    },
    {
      "time": "0428",
      "callsign": "F181",
      "appear_time": "0428",
      "model": "A319",
      "gate": "51B",
      "airport": "SJC",
      "runway": "10R/28L",
      "spot": "S2"
    },
    {
      "time": "0429",
      "callsign": "F182",
      "appear_time": "0429",
      "model": "A319",
      "gate": "52",
      "airport": "SJC",
      "runway": "10R/28L",
      "spot": "S3"
    },
    {
      "time": "0431",
      "callsign": "F183",
      "appear_time": "0431",
      "model": "A319",
      "gate": "54B",
      "airport": "SJC",
      "runway": "10R/28L",
      "spot": "S2"
    },
    {
      "time": "0432",
      "callsign": "F184",
      "appear_time": "0432",
      "model": "A319",
      "gate": "54B",
      "airport": "SJC",
      "runway": "10R/28L",
      "spot": "S3"
    },
    {
      "time": "0433",
      "callsign": "F185",
      "appear_time": "0433",
      "model": "A319",
      "gate": "54B",
      "airport": "SJC",
      "runway": "10R/28L",
      "spot": "S3"
    },
    {
      "time": "0435",
      "callsign": "F186",
      "appear_time": "0435",
      "model": "A319",
      "gate": "54A",
      "airport": "SJC",
      "runway": "10R/28L",
      "spot": "S3"
    },
    {
      "time": "0437",
      "callsign": "F187",
      "appear_time": "0437",
      "model": "A319",
      "gate": "51A",
      "airport": "SJC",
      "runway": "10R/28L",
      "spot": "S2"
    },
    {
      "time": "0438",
      "callsign": "F188",
      "appear_time": "0438",
      "model": "A319",
      "gate": "51A",
      "airport": "SJC",
      "runway": "10R/28L",
      "spot": "S2"
    },
    {
      "time": "0440",
      "callsign": "F189",
      "appear_time": "0440",
      "model": "A319",
      "gate": "53",
      "airport": "SJC",
      "runway": "10R/28L",
      "spot": "S3"
    },
    {
      "time": "0441",
      "callsign": "F190",
      "appear_time": "0441",
      "model": "A319",
      "gate": "51B",
      "airport": "SJC",
      "runway": "10R/28L",
      "spot": "S3"
    },
    {
      "time": "0443",
      "callsign": "F191",
      "appear_time": "0443",
      "model": "A319",
      "gate": "51A",
      "airport": "SJC",
      "runway": "10R/28L",
      "spot": "S3"
    },
    {
      "time": "0446",
      "callsign": "F192",
      "appear_time": "0446",
      "model": "A319",
      "gate": "51A",
      "airport": "SJC",
      "runway": "10R/28L",
      "spot": "S2"
    },
    {
      "time": "0447",
      "callsign": "F193",
      "appear_time": "0447",
      "model": "A319",
      "gate": "52",
      "airport": "SJC",
      "runway": "10R/28L",
      "spot": "S3"
    },
    {
      "time": "0449",
      "callsign": "F194",
      "appear_time": "0449",
      "model": "A319",
      "gate": "51A",
      "airport": "SJC",
      "runway": "10R/28L",
      "spot": "S2"
    },
    {
      "time": "0450",
      "callsign": "F195",
      "appear_time": "0450",
      "model": "A319",
      "gate": "56B",
      "airport": "SJC",
      "runway": "10R/28L",
      "spot": "S2"
    },
    {
      "time": "0451",
      "callsign": "F196",
      "appear_time": "0451",
      "model": "A319",
      "gate": "51A",
      "airport": "SJC",
      "runway": "10R/28L",
      "spot": "S3"
    },
    {
      "time": "0453",
      "callsign": "F197",
      "appear_time": "0453",
      "model": "A319",
      "gate": "55",
      "airport": "SJC",
      "runway": "10R/28L",
      "spot": "S3"
    },
    {
      "time": "0455",
      "callsign": "F198",
      "appear_time": "0455",
      "model": "A319",
      "gate": "51B",
      "airport": "SJC",
      "runway": "10R/28L",
      "spot": "S3"
    },
    {
      "time": "0455",
      "callsign": "F199",
      "appear_time": "0455",
      "model": "A319",
      "gate": "54B",
      "airport": "SJC",
      "runway": "10R/28L",
      "spot": "S3"
    },
    {
      "time": "0457",
      "callsign": "F200",
      "appear_time": "0457",
      "model": "A319",
      "gate": "56A",
      "airport": "SJC",
      "runway": "10R/28L",
      "spot": "S2"
    },
    {
      "time": "0459",
      "callsign": "F201",
      "appear_time": "0459",
      "model": "A319",
      "gate": "57",
      "airport": "SJC",
      "runway": "10R/28L",
      "spot": "S3"
    },
    {
      "time": "0500",
      "callsign": "F202",
      "appear_time": "0500",
      "model": "A319",
      "gate": "55",
      "airport": "SJC",
      "runway": "10R/28L",
      "spot": "S2"
    },
    {
      "time": "0501",
      "callsign": "F203",
      "appear_time": "0501",
      "model": "A319",
      "gate": "57",
      "airport": "SJC",
      "runway": "10R/28L",
      "spot": "S3"
    },
    {
      "time": "0503",
      "callsign": "F204",
      "appear_time": "0503",
      "model": "A319",
      "gate": "50",
      "airport": "SJC",
      "runway": "10R/28L",
      "spot": "S2"
    },
    {
      "time": "0505",
      "callsign": "F205",
      "appear_time": "0505",
      "model": "A319",
      "gate": "54B",
      "airport": "SJC",
      "runway": "10R/28L",
      "spot": "S2"
    },
    {
      "time": "0507",
      "callsign": "F206",
      "appear_time": "0507",
      "model": "A319",
      "gate": "51A",
      "airport": "SJC",
      "runway": "10R/28L",
      "spot": "S3"
    },
    {
      "time": "0509",
      "callsign": "F207",
      "appear_time": "0509",
      "model": "A319",
      "gate": "55",
      "airport": "SJC",
      "runway": "10R/28L",
      "spot": "S3"
    },
    {
      "time": "0511",
      "callsign": "F208",
      "appear_time": "0511",
      "model": "A319",
      "gate": "55",
      "airport": "SJC",
      "runway": "10R/28L",
      "spot": "S3"
    },
    {
      "time": "0512",
      "callsign": "F209",
      "appear_time": "0512",
      "model": "A319",
      "gate": "58A",
      "airport": "SJC",
      "runway": "10R/28L",
      "spot": "S3"
    },
    {
      "time": "0515",
      "callsign": "F210",
      "appear_time": "0515",
      "model": "A319",
      "gate": "56B",
      "airport": "SJC",
      "runway": "10R/28L",
      "spot": "S3"
    },
    {
      "time": "0517",
      "callsign": "F211",
      "appear_time": "0517",
      "model": "A319",
      "gate": "56A",
      "airport": "SJC",
      "runway": "10R/28L",
      "spot": "S2"
    },
    {
      "time": "0519",
      "callsign": "F212",
      "appear_time": "0519",
      "model": "A319",
      "gate": "57",
      "airport": "SJC",
      "runway": "10R/28L",
      "spot": "S2"
    },
    {
      "time": "0520",
      "callsign": "F213",
      "appear_time": "0520",
      "model": "A319",
      "gate": "50",
      "airport": "SJC",
      "runway": "10R/28L",
      "spot": "S2"
    },
    {
      "time": "0522",
      "callsign": "F214",
      "appear_time": "0522",
      "model": "A319",
      "gate": "50",
      "airport": "SJC",
      "runway": "10R/28L",
      "spot": "S2"
    },
    {
      "time": "0524",
      "callsign": "F215",
      "appear_time": "0524",
      "model": "A319",
      "gate": "53",
      "airport": "SJC",
      "runway": "10R/28L",
      "spot": "S3"
    },
    {
      "time": "0526",
      "callsign": "F216",
      "appear_time": "0526",
      "model": "A319",
      "gate": "58B",
      "airport": "SJC",
      "runway": "10R/28L",
      "spot": "S2"
    },
    {
      "time": "0527",
      "callsign": "F217",
      "appear_time": "0527",
      "model": "A319",
      "gate": "55",
      "airport": "SJC",
      "runway": "10R/28L",
      "spot": "S2"
    },
    {
      "time": "0528",
      "callsign": "F218",
      "appear_time": "0528",
      "model": "A319",
      "gate": "55",
      "airport": "SJC",
      "runway": "10R/28L",
      "spot": "S2"
    },
    {
      "time": "0529",
      "callsign": "F219",
      "appear_time": "0529",
      "model": "A319",
      "gate": "51B",
      "airport": "SJC",
      "runway": "10R/28L",
      "spot": "S3"
    },
    {
      "time": "0531",
      "callsign": "F220",
      "appear_time": "0531",
      "model": "A319",
      "gate": "55",
      "airport": "SJC",
      "runway": "10R/28L",
      "spot": "S2"
    },
    {
      "time": "0533",
      "callsign": "F221",
      "appear_time": "0533",
      "model": "A319",
      "gate": "51A",
      "airport": "SJC",
      "runway": "10R/28L",
      "spot": "S3"
    },
    {
      "time": "0534",
      "callsign": "F222",
      "appear_time": "0534",
      "model": "A319",
      "gate": "59",
      "airport": "SJC",
      "runway": "10R/28L",
      "spot": "S2"
    },
    {
      "time": "0535",
      "callsign": "F223",
      "appear_time": "0535",
      "model": "A319",
      "gate": "59",
      "airport": "SJC",
      "runway": "10R/28L",
      "spot": "S3"
    },
    {
      "time": "0536",
      "callsign": "F224",
      "appear_time": "0536",
      "model": "A319",
      "gate": "56B",
      "airport": "SJC",
      "runway": "10R/28L",
      "spot": "S3"
    },
    {
      "time": "0537",
      "callsign": "F225",
      "appear_time": "0537",
      "model": "A319",
      "gate": "56B",
      "airport": "SJC",
      "runway": "10R/28L",
      "spot": "S2"
    },
    {
      "time": "0539",
      "callsign": "F226",
      "appear_time": "0539",
      "model": "A319",
      "gate": "56B",
      "airport": "SJC",
      "runway": "10R/28L",
      "spot": "S2"
    },
    {
      "time": "0541",
      "callsign": "F227",
      "appear_time": "0541",
      "model": "A319",
      "gate": "51B",
      "airport": "SJC",
      "runway": "10R/28L",
      "spot": "S2"
    },
    {
      "time": "0542",
      "callsign": "F228",
      "appear_time": "0542",
      "model": "A319",
      "gate": "58A",
      "airport": "SJC",
      "runway": "10R/28L",
      "spot": "S3"
    },
    {
      "time": "0543",
      "callsign": "F229",
      "appear_time": "0543",
      "model": "A319",
      "gate": "56B",
      "airport": "SJC",
      "runway": "10R/28L",
      "spot": "S2"
    },
    {
      "time": "0545",
      "callsign": "F230",
      "appear_time": "0545",
      "model": "A319",
      "gate": "58A",
      "airport": "SJC",
      "runway": "10R/28L",
      "spot": "S2"
    },
    {
      "time": "0546",
      "callsign": "F231",
      "appear_time": "0546",
      "model": "A319",
      "gate": "54A",
      "airport": "SJC",
      "runway": "10R/28L",
      "spot": "S3"
    },
    {
      "time": "0547",
      "callsign": "F232",
      "appear_time": "0547",
      "model": "A319",
      "gate": "51B",
      "airport": "SJC",
      "runway": "10R/28L",
      "spot": "S2"
    },
    {
      "time": "0549",
      "callsign": "F233",
      "appear_time": "0549",
      "model": "A319",
      "gate": "58B",
      "airport": "SJC",
      "runway": "10R/28L",
      "spot": "S3"
    },
    {
      "time": "0549",
      "callsign": "F234",
      "appear_time": "0549",
      "model": "A319",
      "gate": "51B",
      "airport": "SJC",
      "runway": "10R/28L",
      "spot": "S2"
    },
    {
      "time": "0551",
      "callsign": "F235",
      "appear_time": "0551",
      "model": "A319",
      "gate": "52",
      "airport": "SJC",
      "runway": "10R/28L",
      "spot": "S2"
    },
    {
      "time": "0554",
      "callsign": "F236",
      "appear_time": "0554",
      "model": "A319",
      "gate": "57",
      "airport": "SJC",
      "runway": "10R/28L",
      "spot": "S3"
    },
    {
      "time": "0556",
      "callsign": "F237",
      "appear_time": "0556",
      "model": "A319",
      "gate": "54B",
      "airport": "SJC",
      "runway": "10R/28L",
      "spot": "S2"
    },
    {
      "time": "0558",
      "callsign": "F238",
      "appear_time": "0558",
      "model": "A319",
      "gate": "57",
      "airport": "SJC",
      "runway": "10R/28L",
      "spot": "S3"
    },
    {
      "time": "0559",
      "callsign": "F239",
      "appear_time": "0559",
      "model": "A319",
      "gate": "53",
      "airport": "SJC",
      "runway": "10R/28L",
      "spot": "S2"
    },
    {
      "time": "0601",
      "callsign": "F240",
      "appear_time": "0601",
      "model": "A319",
      "gate": "57",
      "airport": "SJC",
      "runway": "10R/28L",
      "spot": "S2"
    },
    {
      "time": "0602",
      "callsign": "F241",
      "appear_time": "0602",
      "model": "A319",
      "gate": "51A",
      "airport": "SJC",
      "runway": "10R/28L",
      "spot": "S3"
    },
    {
      "time": "0603",
      "callsign": "F242",
      "appear_time": "0603",
      "model": "A319",
      "gate": "58B",
      "airport": "SJC",
      "runway": "10R/28L",
      "spot": "S3"
    },
    {
      "time": "0605",
      "callsign": "F243",
      "appear_time": "0605",
      "model": "A319",
      "gate": "50",
      "airport": "SJC",
      "runway": "10R/28L",
      "spot": "S3"
    },
    {
      "time": "0608",
      "callsign": "F244",
      "appear_time": "0608",
      "model": "A319",
      "gate": "54B",
      "airport": "SJC",
      "runway": "10R/28L",
      "spot": "S3"
    },
    {
      "time": "0609",
      "callsign": "F245",
      "appear_time": "0609",
      "model": "A319",
      "gate": "54B",
      "airport": "SJC",
      "runway": "10R/28L",
      "spot": "S2"
    },
    {
      "time": "0610",
      "callsign": "F246",
      "appear_time": "0610",
      "model": "A319",
      "gate": "51A",
      "airport": "SJC",
      "runway": "10R/28L",
      "spot": "S2"
    },
    {
      "time": "0612",
      "callsign": "F247",
      "appear_time": "0612",
      "model": "A319",
      "gate": "50",
      "airport": "SJC",
      "runway": "10R/28L",
      "spot": "S2"
    },
    {
      "time": "0614",
      "callsign": "F248",
      "appear_time": "0614",
      "model": "A319",
      "gate": "52",
      "airport": "SJC",
      "runway": "10R/28L",
      "spot": "S2"
    },
    {
      "time": "0616",
      "callsign": "F249",
      "appear_time": "0616",
      "model": "A319",
      "gate": "50",
      "airport": "SJC",
      "runway": "10R/28L",
      "spot": "S3"
    },
    {
      "time": "0618",
      "callsign": "F250",
      "appear_time": "0618",
      "model": "A319",
      "gate": "54A",
      "airport": "SJC",
      "runway": "10R/28L",
      "spot": "S3"
    },
    {
      "time": "0619",
      "callsign": "F251",
      "appear_time": "0619",
      "model": "A319",
      "gate": "56B",
      "airport": "SJC",
      "runway": "10R/28L",
      "spot": "S2"
    },
    {
      "time": "0620",
      "callsign": "F252",
      "appear_time": "0620",
      "model": "A319",
      "gate": "56B",
      "airport": "SJC",
      "runway": "10R/28L",
      "spot": "S3"
    },
    {
      "time": "0622",
      "callsign": "F253",
      "appear_time": "0622",
      "model": "A319",
      "gate": "56A",
      "airport": "SJC",
      "runway": "10R/28L",
      "spot": "S2"
    },
    {
      "time": "0624",
      "callsign": "F254",
      "appear_time": "0624",
      "model": "A319",
      "gate": "59",
      "airport": "SJC",
      "runway": "10R/28L",
      "spot": "S3"
    },
    {
      "time": "0625",
      "callsign": "F255",
      "appear_time": "0625",
      "model": "A319",
      "gate": "56B",
      "airport": "SJC",
      "runway": "10R/28L",
      "spot": "S3"
    },
    {
      "time": "0626",
      "callsign": "F256",
      "appear_time": "0626",
      "model": "A319",
      "gate": "55",
      "airport": "SJC",
      "runway": "10R/28L",
      "spot": "S3"
    },
    {
      "time": "0629",
      "callsign": "F257",
      "appear_time": "0629",
      "model": "A319",
      "gate": "59",
      "airport": "SJC",
      "runway": "10R/28L",
      "spot": "S2"
    },
    {
      "time": "0630",
      "callsign": "F258",
      "appear_time": "0630",
      "model": "A319",
      "gate": "57",
      "airport": "SJC",
      "runway": "10R/28L",
      "spot": "S2"
    },
    {
      "time": "0632",
      "callsign": "F259",
      "appear_time": "0632",
      "model": "A319",
      "gate": "56A",
      "airport": "SJC",
      "runway": "10R/28L",
      "spot": "S2"
    },
    {
      "time": "0634",
      "callsign": "F260",
      "appear_time": "0634",
      "model": "A319",
      "gate": "59",
      "airport": "SJC",
      "runway": "10R/28L",
      "spot": "S3"
    },
    {
      "time": "0635",
      "callsign": "F261",
      "appear_time": "0635",
      "model": "A319",
      "gate": "50",
      "airport": "SJC",
      "runway": "10R/28L",
      "spot": "S3"
    },
    {
      "time": "0636",
      "callsign": "F262",
      "appear_time": "0636",
      "model": "A319",
      "gate": "59",
      "airport": "SJC",
      "runway": "10R/28L",
      "spot": "S2"
    },
    {
      "time": "0638",
      "callsign": "F263",
      "appear_time": "0638",
      "model": "A319",
      "gate": "54B",
      "airport": "SJC",
      "runway": "10R/28L",
      "spot": "S2"
    },
    {
      "time": "0640",
      "callsign": "F264",
      "appear_time": "0640",
      "model": "A319",
      "gate": "58A",
      "airport": "SJC",
      "runway": "10R/28L",
      "spot": "S2"
    },
    {
      "time": "0641",
      "callsign": "F265",
      "appear_time": "0641",
      "model": "A319",
      "gate": "51B",
      "airport": "SJC",
      "runway": "10R/28L",
      "spot": "S2"
    },
    {
      "time": "0643",
      "callsign": "F266",
      "appear_time": "0643",
      "model": "A319",
      "gate": "51B",
      "airport": "SJC",
      "runway": "10R/28L",
      "spot": "S3"
    },
    {
      "time": "0645",
      "callsign": "F267",
      "appear_time": "0645",
      "model": "A319",
      "gate": "57",
      "airport": "SJC",
      "runway": "10R/28L",
      "spot": "S3"
    },
    {
      "time": "0645",
      "callsign": "F268",
      "appear_time": "0645",
      "model": "A319",
      "gate": "54A",
      "airport": "SJC",
      "runway": "10R/28L",
      "spot": "S3"
    },
    {
      "time": "0647",
      "callsign": "F269",
      "appear_time": "0647",
      "model": "A319",
      "gate": "59",
      "airport": "SJC",
      "runway": "10R/28L",
      "spot": "S2"
    },
    {
      "time": "0648",
      "callsign": "F270",
      "appear_time": "0648",
      "model": "A319",
      "gate": "56A",
      "airport": "SJC",
      "runway": "10R/28L",
      "spot": "S3"
    },
    {
      "time": "0650",
      "callsign": "F271",
      "appear_time": "0650",
      "model": "A319",
      "gate": "54B",
      "airport": "SJC",
      "runway": "10R/28L",
      "spot": "S3"
    },
    {
      "time": "0651",
      "callsign": "F272",
      "appear_time": "0651",
      "model": "A319",
      "gate": "53",
      "airport": "SJC",
      "runway": "10R/28L",
      "spot": "S3"
    },
    {
      "time": "0654",
      "callsign": "F273",
      "appear_time": "0654",
      "model": "A319",
      "gate": "57",
      "airport": "SJC",
      "runway": "10R/28L",
      "spot": "S3"
    },
    {
      "time": "0656",
      "callsign": "F274",
      "appear_time": "0656",
      "model": "A319",
      "gate": "56B",
      "airport": "SJC",
      "runway": "10R/28L",
      "spot": "S3"
    },
    {
      "time": "0658",
      "callsign": "F275",
      "appear_time": "0658",
      "model": "A319",
      "gate": "50",
      "airport": "SJC",
      "runway": "10R/28L",
      "spot": "S2"
    },
    {
      "time": "0659",
      "callsign": "F276",
      "appear_time": "0659",
      "model": "A319",
      "gate": "59",
      "airport": "SJC",
      "runway": "10R/28L",
      "spot": "S2"
    },
    {
      "time": "0701",
      "callsign": "F277",
      "appear_time": "0701",
      "model": "A319",
      "gate": "51A",
      "airport": "SJC",
      "runway": "10R/28L",
      "spot": "S3"
    },
    {
      "time": "0702",
      "callsign": "F278",
      "appear_time": "0702",
      "model": "A319",
      "gate": "58A",
      "airport": "SJC",
      "runway": "10R/28L",
      "spot": "S2"
    },
    {
      "time": "0704",
      "callsign": "F279",
      "appear_time": "0704",
      "model": "A319",
      "gate": "51B",
      "airport": "SJC",
      "runway": "10R/28L",
      "spot": "S3"
    },
    {
      "time": "0706",
      "callsign": "F280",
      "appear_time": "0706",
      "model": "A319",
      "gate": "57",
      "airport": "SJC",
      "runway": "10R/28L",
      "spot": "S2"
    },
    {
      "time": "0707",
      "callsign": "F281",
      "appear_time": "0707",
      "model": "A319",
      "gate": "58B",
      "airport": "SJC",
      "runway": "10R/28L",
      "spot": "S2"
    },
    {
      "time": "0708",
      "callsign": "F282",
      "appear_time": "0708",
      "model": "A319",
      "gate": "57",
      "airport": "SJC",
      "runway": "10R/28L",
      "spot": "S2"
    },
    {
      "time": "0710",
      "callsign": "F283",
      "appear_time": "0710",
      "model": "A319",
      "gate": "57",
      "airport": "SJC",
      "runway": "10R/28L",
      "spot": "S3"
    },
    {
      "time": "0711",
      "callsign": "F284",
      "appear_time": "0711",
      "model": "A319",
      "gate": "52",
      "airport": "SJC",
      "runway": "10R/28L",
      "spot": "S3"
    },
    {
      "time": "0713",
      "callsign": "F285",
      "appear_time": "0713",
      "model": "A319",
      "gate": "56B",
      "airport": "SJC",
      "runway": "10R/28L",
      "spot": "S3"
    },
    {
      "time": "0715",
      "callsign": "F286",
      "appear_time": "0715",
      "model": "A319",
      "gate": "56A",
      "airport": "SJC",
      "runway": "10R/28L",
      "spot": "S3"
    },
    {
      "time": "0716",
      "callsign": "F287",
      "appear_time": "0716",
      "model": "A319",
      "gate": "54B",
      "airport": "SJC",
      "runway": "10R/28L",
      "spot": "S2"
    },
    {
      "time": "0717",
      "callsign": "F288",
      "appear_time": "0717",
      "model": "A319",
      "gate": "56A",
      "airport": "SJC",
      "runway": "10R/28L",
      "spot": "S3"
    },
    {
      "time": "0718",
      "callsign": "F289",
      "appear_time": "0718",
      "model": "A319",
      "gate": "56A",
      "airport": "SJC",
      "runway": "10R/28L",
      "spot": "S3"
    },
    {
      "time": "0720",
      "callsign": "F290",
      "appear_time": "0720",
      "model": "A319",
      "gate": "54B",
      "airport": "SJC",
      "runway": "10R/28L",
      "spot": "S2"
    },
    {
      "time": "0722",
      "callsign": "F291",
      "appear_time": "0722",
      "model": "A319",
      "gate": "56A",
      "airport": "SJC",
      "runway": "10R/28L",
      "spot": "S2"
    },
    {
      "time": "0723",
      "callsign": "F292",
      "appear_time": "0723",
      "model": "A319",
      "gate": "56B",
      "airport": "SJC",
      "runway": "10R/28L",
      "spot": "S2"
    },
    {
      "time": "0725",
      "callsign": "F293",
      "appear_time": "0725",
      "model": "A319",
      "gate": "56A",
      "airport": "SJC",
      "runway": "10R/28L",
      "spot": "S3"
    },
    {
      "time": "0726",
      "callsign": "F294",
      "appear_time": "0726",
      "model": "A319",
      "gate": "51A",
      "airport": "SJC",
      "runway": "10R/28L",
      "spot": "S2"
    },
    {
      "time": "0728",
      "callsign": "F295",
      "appear_time": "0728",
      "model": "A319",
      "gate": "52",
      "airport": "SJC",
      "runway": "10R/28L",
      "spot": "S3"
    },
    {
      "time": "0729",
      "callsign": "F296",
      "appear_time": "0729",
      "model": "A319",
      "gate": "58B",
      "airport": "SJC",
      "runway": "10R/28L",
      "spot": "S3"
    },
    {
      "time": "0731",
      "callsign": "F297",
      "appear_time": "0731",
      "model": "A319",
      "gate": "56B",
      "airport": "SJC",
      "runway": "10R/28L",
      "spot": "S2"
    },
    {
      "time": "0732",
      "callsign": "F298",
      "appear_time": "0732",
      "model": "A319",
      "gate": "52",
      "airport": "SJC",
      "runway": "10R/28L",
      "spot": "S3"
    },
    {
      "time": "0735",
      "callsign": "F299",
      "appear_time": "0735",
      "model": "A319",
      "gate": "57",
      "airport": "SJC",
      "runway": "10R/28L",
      "spot": "S3"
    },
    {
      "time": "0737",
      "callsign": "F300",
      "appear_time": "0737",
      "model": "A319",
      "gate": "56A",
      "airport": "SJC",
      "runway": "10R/28L",
      "spot": "S3"
    },
    {
      "time": "0738",
      "callsign": "F301",
      "appear_time": "0738",
      "model": "A319",
      "gate": "50",
      "airport": "SJC",
      "runway": "10R/28L",
      "spot": "S3"
    },
    {
      "time": "0740",
      "callsign": "F302",
      "appear_time": "0740",
      "model": "A319",
      "gate": "51A",
      "airport": "SJC",
      "runway": "10R/28L",
      "spot": "S2"
    },
    {
      "time": "0741",
      "callsign": "F303",
      "appear_time": "0741",
      "model": "A319",
      "gate": "51A",
      "airport": "SJC",
      "runway": "10R/28L",
      "spot": "S2"
    },
    {
      "time": "0742",
      "callsign": "F304",
      "appear_time": "0742",
      "model": "A319",
      "gate": "50",
      "airport": "SJC",
      "runway": "10R/28L",
      "spot": "S3"
    },
    {
      "time": "0744",
      "callsign": "F305",
      "appear_time": "0744",
      "model": "A319",
      "gate": "51A",
      "airport": "SJC",
      "runway": "10R/28L",
      "spot": "S3"
    },
    {
      "time": "0745",
      "callsign": "F306",
      "appear_time": "0745",
      "model": "A319",
      "gate": "50",
      "airport": "SJC",
      "runway": "10R/28L",
      "spot": "S3"
    },
    {
      "time": "0746",
      "callsign": "F307",
      "appear_time": "0746",
      "model": "A319",
      "gate": "50",
      "airport": "SJC",
      "runway": "10R/28L",
      "spot": "S2"
    },
    {
      "time": "0748",
      "callsign": "F308",
      "appear_time": "0748",
      "model": "A319",
      "gate": "54A",
      "airport": "SJC",
      "runway": "10R/28L",
      "spot": "S3"
    },
    {
      "time": "0750",
      "callsign": "F309",
      "appear_time": "0750",
      "model": "A319",
      "gate": "59",
      "airport": "SJC",
      "runway": "10R/28L",
      "spot": "S2"
    },
    {
      "time": "0751",
      "callsign": "F310",
      "appear_time": "0751",
      "model": "A319",
      "gate": "51A",
      "airport": "SJC",
      "runway": "10R/28L",
      "spot": "S2"
    },
    {
      "time": "0753",
      "callsign": "F311",
      "appear_time": "0753",
      "model": "A319",
      "gate": "53",
      "airport": "SJC",
      "runway": "10R/28L",
      "spot": "S2"
    },
    {
      "time": "0755",
      "callsign": "F312",
      "appear_time": "0755",
      "model": "A319",
      "gate": "59",
      "airport": "SJC",
      "runway": "10R/28L",
      "spot": "S2"
    },
    {
      "time": "0757",
      "callsign": "F313",
      "appear_time": "0757",
      "model": "A319",
      "gate": "54A",
      "airport": "SJC",
      "runway": "10R/28L",
      "spot": "S2"
    },
    {
      "time": "0758",
      "callsign": "F314",
      "appear_time": "0758",
      "model": "A319",
      "gate": "59",
      "airport": "SJC",
      "runway": "10R/28L",
      "spot": "S3"
    },
    {
      "time": "0800",
      "callsign": "F315",
      "appear_time": "0800",
      "model": "A319",
      "gate": "55",
      "airport": "SJC",
      "runway": "10R/28L",
      "spot": "S3"
    },
    {
      "time": "0801",
      "callsign": "F316",
      "appear_time": "0801",
      "model": "A319",
      "gate": "54A",
      "airport": "SJC",
      "runway": "10R/28L",
      "spot": "S2"
    },
    {
      "time": "0802",
      "callsign": "F317",
      "appear_time": "0802",
      "model": "A319",
      "gate": "54B",
      "airport": "SJC",
      "runway": "10R/28L",
      "spot": "S3"
    },
    {
      "time": "0804",
      "callsign": "F318",
      "appear_time": "0804",
      "model": "A319",
      "gate": "51B",
      "airport": "SJC",
      "runway": "10R/28L",
      "spot": "S2"
    },
    {
      "time": "0805",
      "callsign": "F319",
      "appear_time": "0805",
      "model": "A319",
      "gate": "54A",
      "airport": "SJC",
      "runway": "10R/28L",
      "spot": "S2"
    },
    {
      "time": "0806",
      "callsign": "F320",
      "appear_time": "0806",
      "model": "A319",
      "gate": "51B",
      "airport": "SJC",
      "runway": "10R/28L",
      "spot": "S2"
    },
    {
      "time": "0808",
      "callsign": "F321",
      "appear_time": "0808",
      "model": "A319",
      "gate": "57",
      "airport": "SJC",
      "runway": "10R/28L",
      "spot": "S3"
    },
    {
      "time": "0810",
      "callsign": "F322",
      "appear_time": "0810",
      "model": "A319",
      "gate": "52",
      "airport": "SJC",
      "runway": "10R/28L",
      "spot": "S2"
    },
    {
      "time": "0811",
      "callsign": "F323",
      "appear_time": "0811",
      "model": "A319",
      "gate": "56B",
      "airport": "SJC",
      "runway": "10R/28L",
      "spot": "S2"
    },
    {
      "time": "0812",
      "callsign": "F324",
      "appear_time": "0812",
      "model": "A319",
      "gate": "51B",
      "airport": "SJC",
      "runway": "10R/28L",
      "spot": "S3"
    },
    {
      "time": "0813",
      "callsign": "F325",
      "appear_time": "0813",
      "model": "A319",
      "gate": "50",
      "airport": "SJC",
      "runway": "10R/28L",
      "spot": "S3"
    },
    {
      "time": "0815",
      "callsign": "F326",
      "appear_time": "0815",
      "model": "A319",
      "gate": "53",
      "airport": "SJC",
      "runway": "10R/28L",
      "spot": "S2"
    },
    {
      "time": "0817",
      "callsign": "F327",
      "appear_time": "0817",
      "model": "A319",
      "gate": "58A",
      "airport": "SJC",
      "runway": "10R/28L",
      "spot": "S3"
    },
    {
      "time": "0818",
      "callsign": "F328",
      "appear_time": "0818",
      "model": "A319",
      "gate": "56B",
      "airport": "SJC",
      "runway": "10R/28L",
      "spot": "S3"
    },
    {
      "time": "0818",
      "callsign": "F329",
      "appear_time": "0818",
      "model": "A319",
      "gate": "56A",
      "airport": "SJC",
      "runway": "10R/28L",
      "spot": "S2"
    },
    {
      "time": "0820",
      "callsign": "F330",
      "appear_time": "0820",
      "model": "A319",
      "gate": "58B",
      "airport": "SJC",
      "runway": "10R/28L",
      "spot": "S2"
    },
    {
      "time": "0822",
      "callsign": "F331",
      "appear_time": "0822",
      "model": "A319",
      "gate": "51A",
      "airport": "SJC",
      "runway": "10R/28L",
      "spot": "S3"
    },
    {
      "time": "0824",
      "callsign": "F332",
      "appear_time": "0824",
      "model": "A319",
      "gate": "56B",
      "airport": "SJC",
      "runway": "10R/28L",
      "spot": "S3"
    },
    {
      "time": "0825",
      "callsign": "F333",
      "appear_time": "0825",
      "model": "A319",
      "gate": "59",
      "airport": "SJC",
      "runway": "10R/28L",
      "spot": "S3"
    },
    {
      "time": "0826",
      "callsign": "F334",
      "appear_time": "0826",
      "model": "A319",
      "gate": "59",
      "airport": "SJC",
      "runway": "10R/28L",
      "spot": "S2"
    },
    {
      "time": "0829",
      "callsign": "F335",
      "appear_time": "0829",
      "model": "A319",
      "gate": "56A",
      "airport": "SJC",
      "runway": "10R/28L",
      "spot": "S2"
    },
    {
      "time": "0830",
      "callsign": "F336",
      "appear_time": "0830",
      "model": "A319",
      "gate": "58B",
      "airport": "SJC",
      "runway": "10R/28L",
      "spot": "S2"
    },
    {
      "time": "0833",
      "callsign": "F337",
      "appear_time": "0833",
      "model": "A319",
      "gate": "57",
      "airport": "SJC",
      "runway": "10R/28L",
      "spot": "S3"
    },
    {
      "time": "0835",
      "callsign": "F338",
      "appear_time": "0835",
      "model": "A319",
      "gate": "58B",
      "airport": "SJC",
      "runway": "10R/28L",
      "spot": "S3"
    },
    {
      "time": "0836",
      "callsign": "F339",
      "appear_time": "0836",
      "model": "A319",
      "gate": "50",
      "airport": "SJC",
      "runway": "10R/28L",
      "spot": "S2"
    },
    {
      "time": "0836",
      "callsign": "F340",
      "appear_time": "0836",
      "model": "A319",
      "gate": "50",
      "airport": "SJC",
      "runway": "10R/28L",
      "spot": "S3"
    },
    {
      "time": "0838",
      "callsign": "F341",
      "appear_time": "0838",
      "model": "A319",
      "gate": "51B",
      "airport": "SJC",
      "runway": "10R/28L",
      "spot": "S3"
    },
    {
      "time": "0840",
      "callsign": "F342",
      "appear_time": "0840",
      "model": "A319",
      "gate": "52",
      "airport": "SJC",
      "runway": "10R/28L",
      "spot": "S3"
    },
    {
      "time": "0841",
      "callsign": "F343",
      "appear_time": "0841",
      "model": "A319",
      "gate": "56A",
      "airport": "SJC",
      "runway": "10R/28L",
      "spot": "S3"
    },
    {
      "time": "0843",
      "callsign": "F344",
      "appear_time": "0843",
      "model": "A319",
      "gate": "50",
      "airport": "SJC",
      "runway": "10R/28L",
      "spot": "S3"
    },
    {
      "time": "0844",
      "callsign": "F345",
      "appear_time": "0844",
      "model": "A319",
      "gate": "53",
      "airport": "SJC",
      "runway": "10R/28L",
      "spot": "S3"
    },
    {
      "time": "0846",
      "callsign": "F346",
      "appear_time": "0846",
      "model": "A319",
      "gate": "51A",
      "airport": "SJC",
      "runway": "10R/28L",
      "spot": "S3"
    },
    {
      "time": "0847",
      "callsign": "F347",
      "appear_time": "0847",
      "model": "A319",
      "gate": "58A",
      "airport": "SJC",
      "runway": "10R/28L",
      "spot": "S3"
    },
    {
      "time": "0848",
      "callsign": "F348",
      "appear_time": "0848",
      "model": "A319",
      "gate": "53",
      "airport": "SJC",
      "runway": "10R/28L",
      "spot": "S3"
    },
    {
      "time": "0850",
      "callsign": "F349",
      "appear_time": "0850",
      "model": "A319",
      "gate": "51B",
      "airport": "SJC",
      "runway": "10R/28L",
      "spot": "S3"
    },
    {
      "time": "0851",
      "callsign": "F350",
      "appear_time": "0851",
      "model": "A319",
      "gate": "54A",
      "airport": "SJC",
      "runway": "10R/28L",
      "spot": "S2"
    },
    {
      "time": "0852",
      "callsign": "F351",
      "appear_time": "0852",
      "model": "A319",
      "gate": "51B",
      "airport": "SJC",
      "runway": "10R/28L",
      "spot": "S3"
    },
    {
      "time": "0854",
      "callsign": "F352",
      "appear_time": "0854",
      "model": "A319",
      "gate": "53",
      "airport": "SJC",
      "runway": "10R/28L",
      "spot": "S3"
    },
    {
      "time": "0854",
      "callsign": "F353",
      "appear_time": "0854",
      "model": "A319",
      "gate": "58A",
      "airport": "SJC",
      "runway": "10R/28L",
      "spot": "S2"
    },
    {
      "time": "0856",
      "callsign": "F354",
      "appear_time": "0856",
      "model": "A319",
      "gate": "57",
      "airport": "SJC",
      "runway": "10R/28L",
      "spot": "S2"
    },
    {
      "time": "0857",
      "callsign": "F355",
      "appear_time": "0857",
      "model": "A319",
      "gate": "51A",
      "airport": "SJC",
      "runway": "10R/28L",
      "spot": "S3"
    },
    {
      "time": "0857",
      "callsign": "F356",
      "appear_time": "0857",
      "model": "A319",
      "gate": "54A",
      "airport": "SJC",
      "runway": "10R/28L",
      "spot": "S2"
    },
    {
      "time": "0859",
      "callsign": "F357",
      "appear_time": "0859",
      "model": "A319",
      "gate": "54B",
      "airport": "SJC",
      "runway": "10R/28L",
      "spot": "S3"
    }
  ]
}